[
  {
    "id": "c1_001",
    "kanji": "それ",
    "kana": "それ",
    "fr": "cela / ça",
    "ex": "それを取ってください。"
  },
  {
    "id": "c1_002",
    "kanji": "見る",
    "kana": "みる",
    "fr": "regarder",
    "ex": "毎日テレビを見ます。"
  },
  {
    "id": "c1_003",
    "kanji": "円",
    "kana": "えん",
    "fr": "cercle / yen",
    "ex": "このペンは百円です。"
  },
  {
    "id": "c1_004",
    "kanji": "多い",
    "kana": "おおい",
    "fr": "beaucoup",
    "ex": "この町は人が多いです。"
  },
  {
    "id": "c1_005",
    "kanji": "家",
    "kana": "うち",
    "fr": "maison",
    "ex": "私の家はあそこです。"
  },
  {
    "id": "c1_006",
    "kanji": "これ",
    "kana": "これ",
    "fr": "ceci / celui-ci",
    "ex": "これは私の本です。"
  },
  {
    "id": "c1_007",
    "kanji": "新しい",
    "kana": "あたらしい",
    "fr": "nouveau",
    "ex": "新しい車を買いました。"
  },
  {
    "id": "c1_008",
    "kanji": "私",
    "kana": "わたし",
    "fr": "je",
    "ex": "私は学生です。"
  },
  {
    "id": "c1_009",
    "kanji": "仕事",
    "kana": "しごと",
    "fr": "travail",
    "ex": "私の仕事は先生です。"
  },
  {
    "id": "c1_010",
    "kanji": "始める",
    "kana": "はじめる",
    "fr": "commencer",
    "ex": "今からテストを始めます。"
  },
  {
    "id": "c1_011",
    "kanji": "なる",
    "kana": "なる",
    "fr": "devenir",
    "ex": "将来、医者になりたいです。"
  },
  {
    "id": "c1_012",
    "kanji": "する",
    "kana": "する",
    "fr": "faire",
    "ex": "週末はテニスをします。"
  },
  {
    "id": "c1_013",
    "kanji": "出る",
    "kana": "でる",
    "fr": "sortir",
    "ex": "部屋を出ます。"
  },
  {
    "id": "c1_014",
    "kanji": "使う",
    "kana": "つかう",
    "fr": "utiliser",
    "ex": "このパソコンを使ってもいいですか。"
  },
  {
    "id": "c1_015",
    "kanji": "ところ",
    "kana": "ところ",
    "fr": "lieu",
    "ex": "ここは静かなところです。"
  },
  {
    "id": "c1_016",
    "kanji": "思う",
    "kana": "おもう",
    "fr": "penser",
    "ex": "明日は雨が降ると思います。"
  },
  {
    "id": "c1_017",
    "kanji": "持つ",
    "kana": "もつ",
    "fr": "avoir",
    "ex": "私はかばんを持っています。"
  },
  {
    "id": "c1_018",
    "kanji": "時間",
    "kana": "じかん",
    "fr": "temps",
    "ex": "今、時間がありません。"
  },
  {
    "id": "c1_019",
    "kanji": "今年",
    "kana": "ことし",
    "fr": "cette année",
    "ex": "今年、日本へ行きます。"
  },
  {
    "id": "c1_020",
    "kanji": "知る",
    "kana": "しる",
    "fr": "savoir",
    "ex": "そのニュースを知っていますか。"
  },
  {
    "id": "c1_021",
    "kanji": "作る",
    "kana": "つくる",
    "fr": "faire",
    "ex": "母がケーキを作りました。"
  },
  {
    "id": "c1_022",
    "kanji": "同じ",
    "kana": "おなじ",
    "fr": "même",
    "ex": "私の車はあなたのと同じです。"
  },
  {
    "id": "c1_023",
    "kanji": "今",
    "kana": "いま",
    "fr": "maintenant",
    "ex": "今、何時ですか。"
  },
  {
    "id": "c1_024",
    "kanji": "続く",
    "kana": "つづく",
    "fr": "continuer",
    "ex": "雨が三日続きました。"
  },
  {
    "id": "c1_025",
    "kanji": "国",
    "kana": "くに",
    "fr": "pays",
    "ex": "あなたの国はどこですか。"
  },
  {
    "id": "c1_026",
    "kanji": "未だ",
    "kana": "まだ",
    "fr": "toujours",
    "ex": "彼はまだ来ていません。"
  },
  {
    "id": "c1_027",
    "kanji": "やる",
    "kana": "やる",
    "fr": "faire",
    "ex": "一緒にゲームをやろう。"
  },
  {
    "id": "c1_028",
    "kanji": "言う",
    "kana": "いう",
    "fr": "dire",
    "ex": "彼は「ありがとう」と言いました。"
  },
  {
    "id": "c1_029",
    "kanji": "少ない",
    "kana": "すくない",
    "fr": "peu",
    "ex": "今日は学生が少ないです。"
  },
  {
    "id": "c1_030",
    "kanji": "行く",
    "kana": "いく",
    "fr": "aller",
    "ex": "明日、学校へ行きます。"
  },
  {
    "id": "c1_031",
    "kanji": "決める",
    "kana": "きめる",
    "fr": "décider",
    "ex": "メニューを決めましたか。"
  },
  {
    "id": "c1_032",
    "kanji": "高い",
    "kana": "たかい",
    "fr": "cher",
    "ex": "この本はとても高いです。"
  },
  {
    "id": "c1_033",
    "kanji": "考える",
    "kana": "かんがえる",
    "fr": "réfléchir",
    "ex": "少し考えさせてください。"
  },
  {
    "id": "c1_034",
    "kanji": "感じる",
    "kana": "かんじる",
    "fr": "sentir",
    "ex": "寒さを感じます。"
  },
  {
    "id": "c1_035",
    "kanji": "子供",
    "kana": "こども",
    "fr": "enfant",
    "ex": "公園で子供が遊んでいます。"
  },
  {
    "id": "c1_036",
    "kanji": "そう",
    "kana": "そう",
    "fr": "oui / c'est ça",
    "ex": "はい、そうです。"
  },
  {
    "id": "c1_037",
    "kanji": "大学",
    "kana": "だいがく",
    "fr": "université",
    "ex": "兄は大学で勉強しています。"
  },
  {
    "id": "c1_038",
    "kanji": "もう",
    "kana": "もう",
    "fr": "déjà",
    "ex": "もう宿題をしましたか。"
  },
  {
    "id": "c1_039",
    "kanji": "近く",
    "kana": "ちかく",
    "fr": "près",
    "ex": "駅の近くに住んでいます。"
  },
  {
    "id": "c1_040",
    "kanji": "入れる",
    "kana": "いれる",
    "fr": "mettre dedans",
    "ex": "コーヒーに砂糖を入れます。"
  },
  {
    "id": "c1_041",
    "kanji": "学生",
    "kana": "がくせい",
    "fr": "étudiant",
    "ex": "私は学生です。"
  },
  {
    "id": "c1_042",
    "kanji": "午後",
    "kana": "ごご",
    "fr": "après-midi",
    "ex": "午後から雨が降ります。"
  },
  {
    "id": "c1_043",
    "kanji": "長い",
    "kana": "ながい",
    "fr": "long",
    "ex": "夏休みは長いです。"
  },
  {
    "id": "c1_044",
    "kanji": "本",
    "kana": "ほん",
    "fr": "livre",
    "ex": "毎晩、本を読みます。"
  },
  {
    "id": "c1_045",
    "kanji": "よく",
    "kana": "よく",
    "fr": "souvent",
    "ex": "私はよく映画を見ます。"
  },
  {
    "id": "c1_046",
    "kanji": "彼女",
    "kana": "かのじょ",
    "fr": "elle",
    "ex": "彼女はとてもきれいです。"
  },
  {
    "id": "c1_047",
    "kanji": "聞く",
    "kana": "きく",
    "fr": "écouter",
    "ex": "音楽を聞くのが好きです。"
  },
  {
    "id": "c1_048",
    "kanji": "どう",
    "kana": "どう",
    "fr": "comment",
    "ex": "このパソコンはどうですか。"
  },
  {
    "id": "c1_049",
    "kanji": "生きる",
    "kana": "いきる",
    "fr": "vivre",
    "ex": "一生懸命に生きる。"
  },
  {
    "id": "c1_050",
    "kanji": "言葉",
    "kana": "ことば",
    "fr": "mots",
    "ex": "日本語の言葉を覚えます。"
  },
  {
    "id": "c1_051",
    "kanji": "顔",
    "kana": "かお",
    "fr": "visage",
    "ex": "朝、顔を洗います。"
  },
  {
    "id": "c1_052",
    "kanji": "どこ",
    "kana": "どこ",
    "fr": "où",
    "ex": "トイレはどこですか。"
  },
  {
    "id": "c1_053",
    "kanji": "一つ",
    "kana": "ひとつ",
    "fr": "un",
    "ex": "りんごを一つください。"
  },
  {
    "id": "c1_054",
    "kanji": "あげる",
    "kana": "あげる",
    "fr": "donner",
    "ex": "友達にプレゼントをあげます。"
  },
  {
    "id": "c1_055",
    "kanji": "こう",
    "kana": "こう",
    "fr": "comme ça",
    "ex": "こうやって作ります。"
  },
  {
    "id": "c1_056",
    "kanji": "学校",
    "kana": "がっこう",
    "fr": "école",
    "ex": "学校は八時に始まります。"
  },
  {
    "id": "c1_057",
    "kanji": "くれる",
    "kana": "くれる",
    "fr": "donner (quand quelqu'un donne au locuteur)",
    "ex": "姉が時計をくれました。"
  },
  {
    "id": "c1_058",
    "kanji": "起きる",
    "kana": "おきる",
    "fr": "se lever",
    "ex": "毎朝六時に起きます。"
  },
  {
    "id": "c1_059",
    "kanji": "春",
    "kana": "はる",
    "fr": "printemps",
    "ex": "春は花が咲きます。"
  },
  {
    "id": "c1_060",
    "kanji": "午前",
    "kana": "ごぜん",
    "fr": "matin",
    "ex": "午前中は忙しいです。"
  },
  {
    "id": "c1_061",
    "kanji": "買う",
    "kana": "かう",
    "fr": "acheter",
    "ex": "スーパーでパンを買いました。"
  },
  {
    "id": "c1_062",
    "kanji": "別",
    "kana": "べつ",
    "fr": "un autre",
    "ex": "別の本を見せてください。"
  },
  {
    "id": "c1_063",
    "kanji": "終わる",
    "kana": "おわる",
    "fr": "fin",
    "ex": "授業は三時に終わります。"
  },
  {
    "id": "c1_064",
    "kanji": "若い",
    "kana": "わかい",
    "fr": "jeune",
    "ex": "彼はまだ若いです。"
  },
  {
    "id": "c1_065",
    "kanji": "かなり",
    "kana": "かなり",
    "fr": "joli / assez",
    "ex": "今日はかなり寒いです。"
  },
  {
    "id": "c1_066",
    "kanji": "置く",
    "kana": "おく",
    "fr": "mettre",
    "ex": "かばんを机の上に置きます。"
  },
  {
    "id": "c1_067",
    "kanji": "住む",
    "kana": "すむ",
    "fr": "habiter",
    "ex": "東京に住んでいます。"
  },
  {
    "id": "c1_068",
    "kanji": "戻る",
    "kana": "もどる",
    "fr": "retour",
    "ex": "すぐに戻ります。"
  },
  {
    "id": "c1_069",
    "kanji": "働く",
    "kana": "はたらく",
    "fr": "travail",
    "ex": "会社で働いています。"
  },
  {
    "id": "c1_070",
    "kanji": "後",
    "kana": "あと",
    "fr": "arrière",
    "ex": "授業の後で、テニスをします。"
  },
  {
    "id": "c1_071",
    "kanji": "先生",
    "kana": "せんせい",
    "fr": "professeur",
    "ex": "田中さんは日本語の先生です。"
  },
  {
    "id": "c1_072",
    "kanji": "立つ",
    "kana": "たつ",
    "fr": "se lever / être debout",
    "ex": "そこに立ってください。"
  },
  {
    "id": "c1_073",
    "kanji": "気",
    "kana": "き",
    "fr": "air",
    "ex": "気をつけてください。"
  },
  {
    "id": "c1_074",
    "kanji": "呼ぶ",
    "kana": "よぶ",
    "fr": "appel",
    "ex": "タクシーを呼びました。"
  },
  {
    "id": "c1_075",
    "kanji": "もっと",
    "kana": "もっと",
    "fr": "plus",
    "ex": "もっとゆっくり話してください。"
  },
  {
    "id": "c1_076",
    "kanji": "帰る",
    "kana": "かえる",
    "fr": "rentrer à la maison",
    "ex": "早く家に帰りたいです。"
  },
  {
    "id": "c1_077",
    "kanji": "気持ち",
    "kana": "きもち",
    "fr": "sentiment",
    "ex": "今日は気持ちがいいです。"
  },
  {
    "id": "c1_078",
    "kanji": "飛ぶ",
    "kana": "とぶ",
    "fr": "voler",
    "ex": "鳥が空を飛んでいます。"
  },
  {
    "id": "c1_079",
    "kanji": "車",
    "kana": "くるま",
    "fr": "voiture",
    "ex": "車で会社に行きます。"
  },
  {
    "id": "c1_080",
    "kanji": "変える",
    "kana": "かえる",
    "fr": "changement",
    "ex": "予定を変えました。"
  },
  {
    "id": "c1_081",
    "kanji": "広い",
    "kana": "ひろい",
    "fr": "large",
    "ex": "私の部屋は広いです。"
  },
  {
    "id": "c1_082",
    "kanji": "分かる",
    "kana": "わかる",
    "fr": "je comprends",
    "ex": "日本語が少し分かります。"
  },
  {
    "id": "c1_083",
    "kanji": "数",
    "kana": "かず",
    "fr": "nombre",
    "ex": "学生の数が多いです。"
  },
  {
    "id": "c1_084",
    "kanji": "近い",
    "kana": "ちかい",
    "fr": "proche / près",
    "ex": "駅はここから近いです。"
  },
  {
    "id": "c1_085",
    "kanji": "そこ",
    "kana": "そこ",
    "fr": "là",
    "ex": "そこに座ってください。"
  },
  {
    "id": "c1_086",
    "kanji": "走る",
    "kana": "はしる",
    "fr": "courir",
    "ex": "犬が走っています。"
  },
  {
    "id": "c1_087",
    "kanji": "売る",
    "kana": "うる",
    "fr": "vendre",
    "ex": "この店で本を売っています。"
  },
  {
    "id": "c1_088",
    "kanji": "朝",
    "kana": "あさ",
    "fr": "matin",
    "ex": "朝、コーヒーを飲みます。"
  },
  {
    "id": "c1_089",
    "kanji": "教える",
    "kana": "おしえる",
    "fr": "enseigner",
    "ex": "英語を教えています。"
  },
  {
    "id": "c1_090",
    "kanji": "歩く",
    "kana": "あるく",
    "fr": "marcher",
    "ex": "公園を歩きます。"
  },
  {
    "id": "c1_091",
    "kanji": "直ぐ",
    "kana": "すぐ",
    "fr": "immédiatement",
    "ex": "すぐ行きます。"
  },
  {
    "id": "c1_092",
    "kanji": "会う",
    "kana": "あう",
    "fr": "rencontrer",
    "ex": "明日、友達に会います。"
  },
  {
    "id": "c1_093",
    "kanji": "部屋",
    "kana": "へや",
    "fr": "chambre",
    "ex": "部屋を掃除します。"
  },
  {
    "id": "c1_094",
    "kanji": "起こる",
    "kana": "おこる",
    "fr": "arriver",
    "ex": "何が起こりましたか。"
  },
  {
    "id": "c1_095",
    "kanji": "秋",
    "kana": "あき",
    "fr": "automne",
    "ex": "秋は涼しいです。"
  },
  {
    "id": "c1_096",
    "kanji": "難しい",
    "kana": "むずかしい",
    "fr": "difficile",
    "ex": "このテストは難しいです。"
  },
  {
    "id": "c1_097",
    "kanji": "送る",
    "kana": "おくる",
    "fr": "envoyer",
    "ex": "手紙を送りました。"
  },
  {
    "id": "c1_098",
    "kanji": "死ぬ",
    "kana": "しぬ",
    "fr": "mourir",
    "ex": "猫が死にました。"
  },
  {
    "id": "c1_099",
    "kanji": "乗る",
    "kana": "のる",
    "fr": "monter",
    "ex": "電車に乗ります。"
  },
  {
    "id": "c1_100",
    "kanji": "安い",
    "kana": "やすい",
    "fr": "bon marché",
    "ex": "この靴は安いです。"
  },
  {
    "id": "c1_101",
    "kanji": "書く",
    "kana": "かく",
    "fr": "écrire",
    "ex": "ノートに名前を書きます。"
  },
  {
    "id": "c1_102",
    "kanji": "話す",
    "kana": "はなす",
    "fr": "parler",
    "ex": "友達と話します。"
  },
  {
    "id": "c1_103",
    "kanji": "頭",
    "kana": "あたま",
    "fr": "tête",
    "ex": "頭が痛いです。"
  },
  {
    "id": "c1_104",
    "kanji": "体",
    "kana": "からだ",
    "fr": "corps",
    "ex": "体が大きいです。"
  },
  {
    "id": "c1_105",
    "kanji": "ここ",
    "kana": "ここ",
    "fr": "ici",
    "ex": "ここは東京です。"
  },
  {
    "id": "c1_106",
    "kanji": "待つ",
    "kana": "まつ",
    "fr": "attendez",
    "ex": "ちょっと待ってください。"
  },
  {
    "id": "c1_107",
    "kanji": "低い",
    "kana": "ひくい",
    "fr": "bas / petit",
    "ex": "背が低いです。"
  },
  {
    "id": "c1_108",
    "kanji": "もらう",
    "kana": "もらう",
    "fr": "obtenir",
    "ex": "友達に本をもらいました。"
  },
  {
    "id": "c1_109",
    "kanji": "食べる",
    "kana": "たべる",
    "fr": "manger",
    "ex": "ご飯を食べます。"
  },
  {
    "id": "c1_110",
    "kanji": "早い",
    "kana": "はやい",
    "fr": "tôt",
    "ex": "朝早く起きます。"
  },
  {
    "id": "c1_111",
    "kanji": "兄",
    "kana": "あに",
    "fr": "frère aîné",
    "ex": "兄は二十歳です。"
  },
  {
    "id": "c1_112",
    "kanji": "名前",
    "kana": "なまえ",
    "fr": "nom",
    "ex": "あなたの名前は何ですか。"
  },
  {
    "id": "c1_113",
    "kanji": "夫",
    "kana": "おっと",
    "fr": "mari",
    "ex": "夫は会社員です。"
  },
  {
    "id": "c1_114",
    "kanji": "一",
    "kana": "いち",
    "fr": "un",
    "ex": "一から十まで数えます。"
  },
  {
    "id": "c1_115",
    "kanji": "結婚",
    "kana": "けっこん",
    "fr": "mariage",
    "ex": "来年、結婚します。"
  },
  {
    "id": "c1_116",
    "kanji": "親",
    "kana": "おや",
    "fr": "mère",
    "ex": "親に手紙を書きます。"
  },
  {
    "id": "c1_117",
    "kanji": "古い",
    "kana": "ふるい",
    "fr": "vieux",
    "ex": "これは古い本です。"
  },
  {
    "id": "c1_118",
    "kanji": "美しい",
    "kana": "うつくしい",
    "fr": "beau",
    "ex": "美しい花ですね。"
  },
  {
    "id": "c1_119",
    "kanji": "足",
    "kana": "あし",
    "fr": "pieds",
    "ex": "足が長いです。"
  },
  {
    "id": "c1_120",
    "kanji": "次",
    "kana": "つぎ",
    "fr": "suivant",
    "ex": "次の駅で降ります。"
  },
  {
    "id": "c1_121",
    "kanji": "起こす",
    "kana": "おこす",
    "fr": "réveillez-vous",
    "ex": "明日、七時に起こしてください。"
  },
  {
    "id": "c1_122",
    "kanji": "見せる",
    "kana": "みせる",
    "fr": "montrer",
    "ex": "写真を見せてください。"
  },
  {
    "id": "c1_123",
    "kanji": "娘",
    "kana": "むすめ",
    "fr": "fille",
    "ex": "娘は三歳です。"
  },
  {
    "id": "c1_124",
    "kanji": "とても",
    "kana": "とても",
    "fr": "très",
    "ex": "今日はとても寒いです。"
  },
  {
    "id": "c1_125",
    "kanji": "少し",
    "kana": "すこし",
    "fr": "un peu",
    "ex": "砂糖を少し入れます。"
  },
  {
    "id": "c1_126",
    "kanji": "質問",
    "kana": "しつもん",
    "fr": "question",
    "ex": "質問がありますか。"
  },
  {
    "id": "c1_127",
    "kanji": "楽しむ",
    "kana": "たのしむ",
    "fr": "apprécier / s'amuser",
    "ex": "パーティーを楽しみました。"
  },
  {
    "id": "c1_128",
    "kanji": "色",
    "kana": "いろ",
    "fr": "couleur",
    "ex": "好きな色は何ですか。"
  },
  {
    "id": "c1_129",
    "kanji": "みんな",
    "kana": "みんな",
    "fr": "tout le monde",
    "ex": "みんなで歌いましょう。"
  },
  {
    "id": "c1_130",
    "kanji": "取る",
    "kana": "とる",
    "fr": "prendre",
    "ex": "塩を取ってください。"
  },
  {
    "id": "c1_131",
    "kanji": "勉強",
    "kana": "べんきょう",
    "fr": "étude",
    "ex": "毎日日本語を勉強します。"
  },
  {
    "id": "c1_132",
    "kanji": "出来る",
    "kana": "できる",
    "fr": "pouvoir / être capable",
    "ex": "英語を話すことができます。"
  },
  {
    "id": "c1_133",
    "kanji": "短い",
    "kana": "みじかい",
    "fr": "court",
    "ex": "髪が短いです。"
  },
  {
    "id": "c1_134",
    "kanji": "落ちる",
    "kana": "おちる",
    "fr": "tomber",
    "ex": "ペンが落ちました。"
  },
  {
    "id": "c1_135",
    "kanji": "息子",
    "kana": "むすこ",
    "fr": "fils",
    "ex": "息子は小学生です。"
  },
  {
    "id": "c1_136",
    "kanji": "白い",
    "kana": "しろい",
    "fr": "blanc",
    "ex": "白いシャツを着ます。"
  },
  {
    "id": "c1_137",
    "kanji": "誰",
    "kana": "だれ",
    "fr": "qui",
    "ex": "あの人は誰ですか。"
  },
  {
    "id": "c1_138",
    "kanji": "いつも",
    "kana": "いつも",
    "fr": "toujours",
    "ex": "彼はいつも元気です。"
  },
  {
    "id": "c1_139",
    "kanji": "飛行機",
    "kana": "ひこうき",
    "fr": "avion",
    "ex": "飛行機で日本へ行きます。"
  },
  {
    "id": "c1_140",
    "kanji": "勝つ",
    "kana": "かつ",
    "fr": "gagner",
    "ex": "試合に勝ちました。"
  },
  {
    "id": "c1_141",
    "kanji": "病気",
    "kana": "びょうき",
    "fr": "maladie",
    "ex": "病気で学校を休みます。"
  },
  {
    "id": "c1_142",
    "kanji": "冬",
    "kana": "ふゆ",
    "fr": "hiver",
    "ex": "日本の冬は寒いです。"
  },
  {
    "id": "c1_143",
    "kanji": "年",
    "kana": "とし",
    "fr": "année / âge",
    "ex": "年を取ります。"
  },
  {
    "id": "c1_144",
    "kanji": "重い",
    "kana": "おもい",
    "fr": "lourd",
    "ex": "このかばんは重いです。"
  },
  {
    "id": "c1_145",
    "kanji": "胸",
    "kana": "むね",
    "fr": "poitrine",
    "ex": "胸が痛いです。"
  },
  {
    "id": "c1_146",
    "kanji": "読む",
    "kana": "よむ",
    "fr": "lire",
    "ex": "毎日新聞を読みます。"
  },
  {
    "id": "c1_147",
    "kanji": "払う",
    "kana": "はらう",
    "fr": "payer",
    "ex": "お金を払います。"
  },
  {
    "id": "c1_148",
    "kanji": "軽い",
    "kana": "かるい",
    "fr": "léger",
    "ex": "この靴はとても軽いです。"
  },
  {
    "id": "c1_149",
    "kanji": "見つける",
    "kana": "みつける",
    "fr": "trouver",
    "ex": "新しい仕事を見つけました。"
  },
  {
    "id": "c1_150",
    "kanji": "いつ",
    "kana": "いつ",
    "fr": "quand",
    "ex": "誕生日はいつですか。"
  },
  {
    "id": "c1_151",
    "kanji": "友達",
    "kana": "ともだち",
    "fr": "ami",
    "ex": "友達と一緒に遊びます。"
  },
  {
    "id": "c1_152",
    "kanji": "忘れる",
    "kana": "わすれる",
    "fr": "oublier",
    "ex": "宿題を忘れました。"
  },
  {
    "id": "c1_153",
    "kanji": "酒",
    "kana": "さけ",
    "fr": "alcool / saké",
    "ex": "お酒を飲みません。"
  },
  {
    "id": "c1_154",
    "kanji": "どちら",
    "kana": "どちら",
    "fr": "lequel",
    "ex": "どちらが好きですか。"
  },
  {
    "id": "c1_155",
    "kanji": "姉",
    "kana": "あね",
    "fr": "sœur aînée",
    "ex": "姉は東京にいます。"
  },
  {
    "id": "c1_156",
    "kanji": "覚える",
    "kana": "おぼえる",
    "fr": "mémoriser / se souvenir",
    "ex": "漢字を覚えます。"
  },
  {
    "id": "c1_157",
    "kanji": "狭い",
    "kana": "せまい",
    "fr": "étroit",
    "ex": "道が狭いです。"
  },
  {
    "id": "c1_158",
    "kanji": "好き",
    "kana": "すき",
    "fr": "aimer / préféré",
    "ex": "猫が好きです。"
  },
  {
    "id": "c1_159",
    "kanji": "建てる",
    "kana": "たてる",
    "fr": "construire",
    "ex": "新しい家を建てます。"
  },
  {
    "id": "c1_160",
    "kanji": "どれ",
    "kana": "どれ",
    "fr": "lequel",
    "ex": "あなたの傘はどれですか。"
  },
  {
    "id": "c1_161",
    "kanji": "赤い",
    "kana": "あかい",
    "fr": "rouge",
    "ex": "赤い車が好きです。"
  },
  {
    "id": "c1_162",
    "kanji": "今日",
    "kana": "きょう",
    "fr": "aujourd'hui",
    "ex": "今日はいい天気です。"
  },
  {
    "id": "c1_163",
    "kanji": "着る",
    "kana": "きる",
    "fr": "porter (un vêtement)",
    "ex": "コートを着ます。"
  },
  {
    "id": "c1_164",
    "kanji": "笑う",
    "kana": "わらう",
    "fr": "rire / sourire",
    "ex": "彼女はよく笑います。"
  },
  {
    "id": "c1_165",
    "kanji": "一番",
    "kana": "いちばん",
    "fr": "numéro un / le plus",
    "ex": "クラスで一番背が高いです。"
  },
  {
    "id": "c1_166",
    "kanji": "授業",
    "kana": "じゅぎょう",
    "fr": "cours / classe",
    "ex": "授業は三時に終わります。"
  },
  {
    "id": "c1_167",
    "kanji": "週",
    "kana": "しゅう",
    "fr": "semaine",
    "ex": "一週間に三回テニスをします。"
  },
  {
    "id": "c1_168",
    "kanji": "漢字",
    "kana": "かんじ",
    "fr": "kanji",
    "ex": "この漢字が読めますか。"
  },
  {
    "id": "c1_169",
    "kanji": "自転車",
    "kana": "じてんしゃ",
    "fr": "vélo",
    "ex": "自転車で学校に行きます。"
  },
  {
    "id": "c1_170",
    "kanji": "電車",
    "kana": "でんしゃ",
    "fr": "train",
    "ex": "電車に乗ります。"
  },
  {
    "id": "c1_171",
    "kanji": "探す",
    "kana": "さがす",
    "fr": "chercher",
    "ex": "鍵を探しています。"
  },
  {
    "id": "c1_172",
    "kanji": "紙",
    "kana": "かみ",
    "fr": "papier",
    "ex": "紙に名前を書いてください。"
  },
  {
    "id": "c1_173",
    "kanji": "歌う",
    "kana": "うたう",
    "fr": "chanter",
    "ex": "歌を歌うのが好きです。"
  },
  {
    "id": "c1_174",
    "kanji": "遅い",
    "kana": "おそい",
    "fr": "lent / tard",
    "ex": "夜遅くに帰りました。"
  },
  {
    "id": "c1_175",
    "kanji": "首",
    "kana": "くび",
    "fr": "cou",
    "ex": "キリンは首が長いです。"
  },
  {
    "id": "c1_176",
    "kanji": "速い",
    "kana": "はやい",
    "fr": "rapide",
    "ex": "新幹線はとても速いです。"
  },
  {
    "id": "c1_177",
    "kanji": "一緒に",
    "kana": "いっしょに",
    "fr": "ensemble",
    "ex": "一緒にご飯を食べましょう。"
  },
  {
    "id": "c1_178",
    "kanji": "日記",
    "kana": "にっき",
    "fr": "journal intime",
    "ex": "毎日日記を書いています。"
  },
  {
    "id": "c1_179",
    "kanji": "今月",
    "kana": "こんげつ",
    "fr": "ce mois-ci",
    "ex": "今月はとても忙しいです。"
  },
  {
    "id": "c1_180",
    "kanji": "遊ぶ",
    "kana": "あそぶ",
    "fr": "jouer / s'amuser",
    "ex": "公園で友達と遊びます。"
  },
  {
    "id": "c1_181",
    "kanji": "遠い",
    "kana": "とおい",
    "fr": "loin",
    "ex": "駅は家から遠いです。"
  },
  {
    "id": "c1_182",
    "kanji": "弱い",
    "kana": "よわい",
    "fr": "faible",
    "ex": "私はお酒が弱いです。"
  },
  {
    "id": "c1_183",
    "kanji": "耳",
    "kana": "みみ",
    "fr": "oreille",
    "ex": "うさぎは耳が長いです。"
  },
  {
    "id": "c1_184",
    "kanji": "座る",
    "kana": "すわる",
    "fr": "s'asseoir",
    "ex": "椅子に座ってください。"
  },
  {
    "id": "c1_185",
    "kanji": "右",
    "kana": "みぎ",
    "fr": "droite",
    "ex": "次の角を右に曲がってください。"
  },
  {
    "id": "c1_186",
    "kanji": "浴びる",
    "kana": "あびる",
    "fr": "se doucher / prendre (un bain)",
    "ex": "毎朝シャワーを浴びます。"
  },
  {
    "id": "c1_187",
    "kanji": "肩",
    "kana": "かた",
    "fr": "épaule",
    "ex": "肩が痛いです。"
  },
  {
    "id": "c1_188",
    "kanji": "飲む",
    "kana": "のむ",
    "fr": "boire",
    "ex": "水を飲みます。"
  },
  {
    "id": "c1_189",
    "kanji": "寝る",
    "kana": "ねる",
    "fr": "dormir",
    "ex": "十時に寝ます。"
  },
  {
    "id": "c1_190",
    "kanji": "消す",
    "kana": "けす",
    "fr": "éteindre / effacer",
    "ex": "部屋の電気を消してください。"
  },
  {
    "id": "c1_191",
    "kanji": "元気",
    "kana": "げんき",
    "fr": "en forme / énergique",
    "ex": "お元気ですか。"
  },
  {
    "id": "c1_192",
    "kanji": "負ける",
    "kana": "まける",
    "fr": "perdre",
    "ex": "試合に負けました。"
  },
  {
    "id": "c1_193",
    "kanji": "全部",
    "kana": "ぜんぶ",
    "fr": "tout",
    "ex": "ケーキを全部食べました。"
  },
  {
    "id": "c1_194",
    "kanji": "去年",
    "kana": "きょねん",
    "fr": "l'année dernière",
    "ex": "去年、日本へ行きました。"
  },
  {
    "id": "c1_195",
    "kanji": "引く",
    "kana": "ひく",
    "fr": "tirer",
    "ex": "ドアを引いてください。"
  },
  {
    "id": "c1_196",
    "kanji": "図書館",
    "kana": "としょかん",
    "fr": "bibliothèque",
    "ex": "図書館で本を借ります。"
  },
  {
    "id": "c1_197",
    "kanji": "上げる",
    "kana": "あげる",
    "fr": "lever / augmenter",
    "ex": "手を上げてください。"
  },
  {
    "id": "c1_198",
    "kanji": "緑",
    "kana": "みどり",
    "fr": "vert",
    "ex": "緑色のペンを買いました。"
  },
  {
    "id": "c1_199",
    "kanji": "腕",
    "kana": "うで",
    "fr": "bras",
    "ex": "腕が太いです。"
  },
  {
    "id": "c1_200",
    "kanji": "ドア",
    "kana": "ドア",
    "fr": "porte",
    "ex": "ドアを開けてください。"
  },
  {
    "id": "c1_201",
    "kanji": "閉じる",
    "kana": "とじる",
    "fr": "fermer",
    "ex": "本を閉じてください。"
  },
  {
    "id": "c1_202",
    "kanji": "時",
    "kana": "とき",
    "fr": "moment / quand",
    "ex": "子供の時、よく遊びました。"
  },
  {
    "id": "c1_203",
    "kanji": "米",
    "kana": "こめ",
    "fr": "riz (cru)",
    "ex": "スーパーでお米を買います。"
  },
  {
    "id": "c1_204",
    "kanji": "切る",
    "kana": "きる",
    "fr": "couper",
    "ex": "ナイフで肉を切ります。"
  },
  {
    "id": "c1_205",
    "kanji": "線",
    "kana": "せん",
    "fr": "ligne",
    "ex": "ここに線を引いてください。"
  },
  {
    "id": "c1_206",
    "kanji": "決まる",
    "kana": "きまる",
    "fr": "être décidé",
    "ex": "日程が決まりました。"
  },
  {
    "id": "c1_207",
    "kanji": "楽しい",
    "kana": "たのしい",
    "fr": "amusant",
    "ex": "パーティーはとても楽しいです。"
  },
  {
    "id": "c1_208",
    "kanji": "服",
    "kana": "ふく",
    "fr": "vêtements",
    "ex": "新しい服を買いたいです。"
  },
  {
    "id": "c1_209",
    "kanji": "後ろ",
    "kana": "うしろ",
    "fr": "derrière",
    "ex": "家の後ろに公園があります。"
  },
  {
    "id": "c1_210",
    "kanji": "嬉しい",
    "kana": "うれしい",
    "fr": "heureux",
    "ex": "プレゼントをもらって嬉しいです。"
  },
  {
    "id": "c1_211",
    "kanji": "腰",
    "kana": "こし",
    "fr": "hanche / taille",
    "ex": "腰が痛いです。"
  },
  {
    "id": "c1_212",
    "kanji": "日曜日",
    "kana": "にちようび",
    "fr": "dimanche",
    "ex": "日曜日はデパートへ行きます。"
  },
  {
    "id": "c1_213",
    "kanji": "開ける",
    "kana": "あける",
    "fr": "ouvrir",
    "ex": "窓を開けてください。"
  },
  {
    "id": "c1_214",
    "kanji": "昼",
    "kana": "ひる",
    "fr": "midi / jour",
    "ex": "昼ご飯を食べます。"
  },
  {
    "id": "c1_215",
    "kanji": "お母さん",
    "kana": "おかあさん",
    "fr": "mère",
    "ex": "お母さんは元気ですか。"
  },
  {
    "id": "c1_216",
    "kanji": "留学生",
    "kana": "りゅうがくせい",
    "fr": "étudiant international",
    "ex": "彼は中国からの留学生です。"
  },
  {
    "id": "c1_217",
    "kanji": "大学生",
    "kana": "だいがくせい",
    "fr": "étudiant universitaire",
    "ex": "私は大学生です。"
  },
  {
    "id": "c1_218",
    "kanji": "終わり",
    "kana": "おわり",
    "fr": "fin",
    "ex": "今日の授業はこれで終わりです。"
  },
  {
    "id": "c1_219",
    "kanji": "背",
    "kana": "せ",
    "fr": "taille (hauteur) / dos",
    "ex": "兄は背が高いです。"
  },
  {
    "id": "c1_220",
    "kanji": "手伝う",
    "kana": "てつだう",
    "fr": "aider",
    "ex": "母の仕事を手伝います。"
  },
  {
    "id": "c1_221",
    "kanji": "鼻",
    "kana": "はな",
    "fr": "nez",
    "ex": "犬は鼻がいいです。"
  },
  {
    "id": "c1_222",
    "kanji": "起きる",
    "kana": "おきる",
    "fr": "se lever (ou se produire)",
    "ex": "休日は遅く起きます。"
  },
  {
    "id": "c1_223",
    "kanji": "熱い",
    "kana": "あつい",
    "fr": "chaud (au toucher)",
    "ex": "熱いお茶を飲みます。"
  },
  {
    "id": "c1_224",
    "kanji": "載せる",
    "kana": "のせる",
    "fr": "mettre sur / charger",
    "ex": "机の上に本を載せます。"
  },
  {
    "id": "c1_225",
    "kanji": "悲しい",
    "kana": "かなしい",
    "fr": "triste",
    "ex": "映画を見て悲しくなりました。"
  },
  {
    "id": "c1_226",
    "kanji": "愛",
    "kana": "あい",
    "fr": "amour",
    "ex": "家族への愛。"
  },
  {
    "id": "c1_227",
    "kanji": "しゃべる",
    "kana": "しゃべる",
    "fr": "bavarder",
    "ex": "友達とたくさんしゃべりました。"
  },
  {
    "id": "c1_228",
    "kanji": "近く",
    "kana": "ちかく",
    "fr": "près",
    "ex": "学校の近くにレストランがあります。"
  },
  {
    "id": "c1_229",
    "kanji": "甘い",
    "kana": "あまい",
    "fr": "sucré / doux",
    "ex": "このケーキはとても甘いです。"
  },
  {
    "id": "c1_230",
    "kanji": "テーブル",
    "kana": "テーブル",
    "fr": "table",
    "ex": "テーブルの上にりんごがあります。"
  },
  {
    "id": "c1_231",
    "kanji": "食べ物",
    "kana": "たべもの",
    "fr": "nourriture",
    "ex": "日本の食べ物はおいしいです。"
  },
  {
    "id": "c1_232",
    "kanji": "始まる",
    "kana": "はじまる",
    "fr": "commencer",
    "ex": "映画が始まります。"
  },
  {
    "id": "c1_233",
    "kanji": "ゲーム",
    "kana": "ゲーム",
    "fr": "jeu",
    "ex": "毎日ゲームをします。"
  },
  {
    "id": "c1_234",
    "kanji": "十",
    "kana": "じゅう",
    "fr": "dix",
    "ex": "部屋に人が十人います。"
  },
  {
    "id": "c1_235",
    "kanji": "天気",
    "kana": "てんき",
    "fr": "temps / météo",
    "ex": "明日はいい天気です。"
  },
  {
    "id": "c1_236",
    "kanji": "暑い",
    "kana": "あつい",
    "fr": "chaud (climat)",
    "ex": "今日の夏はとても暑いです。"
  },
  {
    "id": "c1_237",
    "kanji": "太い",
    "kana": "ふとい",
    "fr": "épais",
    "ex": "この木は太いです。"
  },
  {
    "id": "c1_238",
    "kanji": "晩",
    "kana": "ばん",
    "fr": "soir / nuit",
    "ex": "晩ご飯を食べましょう。"
  },
  {
    "id": "c1_239",
    "kanji": "土曜日",
    "kana": "どようび",
    "fr": "samedi",
    "ex": "土曜日は休みです。"
  },
  {
    "id": "c1_240",
    "kanji": "神",
    "kana": "かみ",
    "fr": "dieu",
    "ex": "神に祈ります。"
  },
  {
    "id": "c1_241",
    "kanji": "痛い",
    "kana": "いたい",
    "fr": "douloureux / avoir mal",
    "ex": "お腹が痛いです。"
  },
  {
    "id": "c1_242",
    "kanji": "お父さん",
    "kana": "おとうさん",
    "fr": "père",
    "ex": "お父さんは会社員です。"
  },
  {
    "id": "c1_243",
    "kanji": "多分",
    "kana": "たぶん",
    "fr": "peut-être",
    "ex": "明日は多分雨が降ります。"
  },
  {
    "id": "c1_244",
    "kanji": "時計",
    "kana": "とけい",
    "fr": "montre / horloge",
    "ex": "新しい時計を買いました。"
  },
  {
    "id": "c1_245",
    "kanji": "泊まる",
    "kana": "とまる",
    "fr": "passer la nuit",
    "ex": "ホテルに泊まります。"
  },
  {
    "id": "c1_246",
    "kanji": "どうして",
    "kana": "どうして",
    "fr": "pourquoi",
    "ex": "どうして日本語を勉強しますか。"
  },
  {
    "id": "c1_247",
    "kanji": "掛ける",
    "kana": "かける",
    "fr": "accrocher",
    "ex": "壁に絵を掛けます。"
  },
  {
    "id": "c1_248",
    "kanji": "曲がる",
    "kana": "まがる",
    "fr": "tourner / plier",
    "ex": "次の角を右に曲がります。"
  },
  {
    "id": "c1_249",
    "kanji": "おなか",
    "kana": "おなか",
    "fr": "ventre / estomac",
    "ex": "おなかがすきました。"
  },
  {
    "id": "c1_250",
    "kanji": "ミーティング",
    "kana": "ミーティング",
    "fr": "réunion",
    "ex": "今からミーティングがあります。"
  },
  {
    "id": "c1_251",
    "kanji": "閉める",
    "kana": "しめる",
    "fr": "fermer",
    "ex": "窓を閉めてください。"
  },
  {
    "id": "c1_252",
    "kanji": "嫌い",
    "kana": "きらい",
    "fr": "détester",
    "ex": "私は魚が嫌いです。"
  },
  {
    "id": "c1_253",
    "kanji": "金曜日",
    "kana": "きんようび",
    "fr": "vendredi",
    "ex": "金曜日に映画を見ます。"
  },
  {
    "id": "c1_254",
    "kanji": "要る",
    "kana": "いる",
    "fr": "avoir besoin",
    "ex": "お金が要ります。"
  },
  {
    "id": "c1_255",
    "kanji": "無い",
    "kana": "ない",
    "fr": "ne pas avoir / ne pas exister",
    "ex": "時間が無いです。"
  },
  {
    "id": "c1_256",
    "kanji": "黄色い",
    "kana": "きいろい",
    "fr": "jaune",
    "ex": "黄色い花を買いました。"
  },
  {
    "id": "c1_257",
    "kanji": "風邪",
    "kana": "かぜ",
    "fr": "rhume",
    "ex": "風邪を引きました。"
  },
  {
    "id": "c1_258",
    "kanji": "優しい",
    "kana": "やさしい",
    "fr": "gentil",
    "ex": "彼女はとても優しいです。"
  },
  {
    "id": "c1_259",
    "kanji": "晴れる",
    "kana": "はれる",
    "fr": "s'éclaircir / faire beau",
    "ex": "明日は晴れるでしょう。"
  },
  {
    "id": "c1_260",
    "kanji": "大好き",
    "kana": "だいすき",
    "fr": "adorer",
    "ex": "日本のアニメが大好きです。"
  },
  {
    "id": "c1_261",
    "kanji": "茶色",
    "kana": "ちゃいろ",
    "fr": "marron",
    "ex": "茶色の犬がいます。"
  },
  {
    "id": "c1_262",
    "kanji": "汚い",
    "kana": "きたない",
    "fr": "sale",
    "ex": "この部屋は汚いです。"
  },
  {
    "id": "c1_263",
    "kanji": "空く",
    "kana": "すく",
    "fr": "se vider / avoir faim",
    "ex": "お腹が空きました。"
  },
  {
    "id": "c1_264",
    "kanji": "上る",
    "kana": "のぼる",
    "fr": "grimper / monter",
    "ex": "階段を上ります。"
  },
  {
    "id": "c1_265",
    "kanji": "ご飯",
    "kana": "ごはん",
    "fr": "repas / riz",
    "ex": "朝ご飯を食べます。"
  },
  {
    "id": "c1_266",
    "kanji": "日",
    "kana": "にち",
    "fr": "jour",
    "ex": "一日に三回薬を飲みます。"
  },
  {
    "id": "c1_267",
    "kanji": "髪の毛",
    "kana": "かみのけ",
    "fr": "cheveux",
    "ex": "髪の毛が長いです。"
  },
  {
    "id": "c1_268",
    "kanji": "つける",
    "kana": "つける",
    "fr": "allumer / mettre",
    "ex": "部屋の電気をつけてください。"
  },
  {
    "id": "c1_269",
    "kanji": "月曜日",
    "kana": "げつようび",
    "fr": "lundi",
    "ex": "月曜日は学校があります。"
  },
  {
    "id": "c1_270",
    "kanji": "入る",
    "kana": "はいる",
    "fr": "entrer",
    "ex": "部屋に入ります。"
  },
  {
    "id": "c1_271",
    "kanji": "片仮名",
    "kana": "かたかな",
    "fr": "katakana",
    "ex": "片仮名で名前を書きます。"
  },
  {
    "id": "c1_272",
    "kanji": "今週",
    "kana": "こんしゅう",
    "fr": "cette semaine",
    "ex": "今週は忙しいです。"
  },
  {
    "id": "c1_273",
    "kanji": "開く",
    "kana": "ひらく",
    "fr": "ouvrir",
    "ex": "本を開いてください。"
  },
  {
    "id": "c1_274",
    "kanji": "水",
    "kana": "みず",
    "fr": "eau",
    "ex": "冷たい水を飲みます。"
  },
  {
    "id": "c1_275",
    "kanji": "あれ",
    "kana": "あれ",
    "fr": "cela (là-bas)",
    "ex": "あれは私の車です。"
  },
  {
    "id": "c1_276",
    "kanji": "二",
    "kana": "に",
    "fr": "deux",
    "ex": "二人がいます。"
  },
  {
    "id": "c1_277",
    "kanji": "閉まる",
    "kana": "しまる",
    "fr": "se fermer",
    "ex": "ドアが閉まります。"
  },
  {
    "id": "c1_278",
    "kanji": "締める",
    "kana": "しめる",
    "fr": "serrer / attacher",
    "ex": "シートベルトを締めてください。"
  },
  {
    "id": "c1_279",
    "kanji": "まずい",
    "kana": "まずい",
    "fr": "mauvais (goût)",
    "ex": "この料理はまずいです。"
  },
  {
    "id": "c1_280",
    "kanji": "平仮名",
    "kana": "ひらがな",
    "fr": "hiragana",
    "ex": "平仮名を勉強します。"
  },
  {
    "id": "c1_281",
    "kanji": "曇る",
    "kana": "くもる",
    "fr": "s'ennuager",
    "ex": "空が曇っています。"
  },
  {
    "id": "c1_282",
    "kanji": "触る",
    "kana": "さわる",
    "fr": "toucher",
    "ex": "絵に触らないでください。"
  },
  {
    "id": "c1_283",
    "kanji": "駄目",
    "kana": "だめ",
    "fr": "interdit / pas bon",
    "ex": "ここでタバコを吸っては駄目です。"
  },
  {
    "id": "c1_284",
    "kanji": "書き直す",
    "kana": "かきなおす",
    "fr": "réécrire",
    "ex": "レポートを書き直します。"
  },
  {
    "id": "c1_285",
    "kanji": "飲み物",
    "kana": "のみもの",
    "fr": "boisson",
    "ex": "飲み物は何がいいですか。"
  },
  {
    "id": "c1_286",
    "kanji": "木曜日",
    "kana": "もくようび",
    "fr": "jeudi",
    "ex": "木曜日に会いましょう。"
  },
  {
    "id": "c1_287",
    "kanji": "曜日",
    "kana": "ようび",
    "fr": "jour de la semaine",
    "ex": "今日は何曜日ですか。"
  },
  {
    "id": "c1_288",
    "kanji": "そば",
    "kana": "そば",
    "fr": "nouilles soba / sarrasin",
    "ex": "お昼にそばを食べました。"
  },
  {
    "id": "c1_289",
    "kanji": "こっち",
    "kana": "こっち",
    "fr": "par ici",
    "ex": "こっちへ来てください。"
  },
  {
    "id": "c1_290",
    "kanji": "火曜日",
    "kana": "かようび",
    "fr": "mardi",
    "ex": "火曜日は休みです。"
  },
  {
    "id": "c1_291",
    "kanji": "渇く",
    "kana": "かわく",
    "fr": "avoir soif",
    "ex": "喉が渇きました。"
  },
  {
    "id": "c1_292",
    "kanji": "三",
    "kana": "さん",
    "fr": "trois",
    "ex": "三人の学生がいます。"
  },
  {
    "id": "c1_293",
    "kanji": "水曜日",
    "kana": "すいようび",
    "fr": "mercredi",
    "ex": "水曜日にテストがあります。"
  },
  {
    "id": "c1_294",
    "kanji": "二つ",
    "kana": "ふたつ",
    "fr": "deux (objets)",
    "ex": "ケーキを二つください。"
  },
  {
    "id": "c1_295",
    "kanji": "今晩",
    "kana": "こんばん",
    "fr": "ce soir",
    "ex": "今晩、映画を見ます。"
  },
  {
    "id": "c1_296",
    "kanji": "千",
    "kana": "せん",
    "fr": "mille",
    "ex": "これは千円です。"
  },
  {
    "id": "c1_297",
    "kanji": "六つ",
    "kana": "むっつ",
    "fr": "six (objets)",
    "ex": "卵を六つ買いました。"
  },
  {
    "id": "c1_298",
    "kanji": "六日",
    "kana": "むいか",
    "fr": "six jours / le 6 du mois",
    "ex": "六日に出発します。"
  },
  {
    "id": "c1_299",
    "kanji": "お姉さん",
    "kana": "おねえさん",
    "fr": "sœur aînée",
    "ex": "お姉さんはきれいです。"
  },
  {
    "id": "c1_300",
    "kanji": "直る",
    "kana": "なおる",
    "fr": "être réparé",
    "ex": "パソコンが直りました。"
  },
  {
    "id": "c1_301",
    "kanji": "易しい",
    "kana": "やさしい",
    "fr": "facile",
    "ex": "この問題は易しいです。"
  },
  {
    "id": "c1_302",
    "kanji": "辺",
    "kana": "へん",
    "fr": "environs / coin",
    "ex": "この辺に駅はありますか。"
  },
  {
    "id": "c1_303",
    "kanji": "よう",
    "kana": "よう",
    "fr": "apparence / comme",
    "ex": "今日は雨が降るようです。"
  },
  {
    "id": "c1_304",
    "kanji": "お兄さん",
    "kana": "おにいさん",
    "fr": "grand frère",
    "ex": "お兄さんは元気ですか。"
  },
  {
    "id": "c1_305",
    "kanji": "辛い",
    "kana": "からい",
    "fr": "épicé",
    "ex": "このカレーは辛いです。"
  },
  {
    "id": "c1_306",
    "kanji": "八",
    "kana": "はち",
    "fr": "huit",
    "ex": "八時に起きます。"
  },
  {
    "id": "c1_307",
    "kanji": "三日",
    "kana": "みっか",
    "fr": "trois jours / le 3 du mois",
    "ex": "三日間、休みます。"
  },
  {
    "id": "c1_308",
    "kanji": "あそこ",
    "kana": "あそこ",
    "fr": "là-bas",
    "ex": "あそこに銀行があります。"
  },
  {
    "id": "c1_309",
    "kanji": "来る",
    "kana": "くる",
    "fr": "venir",
    "ex": "友達が家に来ます。"
  },
  {
    "id": "c1_310",
    "kanji": "前",
    "kana": "まえ",
    "fr": "avant / devant",
    "ex": "駅の前にいます。"
  },
  {
    "id": "c1_311",
    "kanji": "五日",
    "kana": "いつか",
    "fr": "cinq jours / le 5 du mois",
    "ex": "五日に帰ります。"
  },
  {
    "id": "c1_312",
    "kanji": "一杯",
    "kana": "いっぱい",
    "fr": "plein / une tasse",
    "ex": "お腹が一杯です。"
  },
  {
    "id": "c1_313",
    "kanji": "九",
    "kana": "きゅう",
    "fr": "neuf",
    "ex": "九時に寝ます。"
  },
  {
    "id": "c1_314",
    "kanji": "酸っぱい",
    "kana": "すっぱい",
    "fr": "acide",
    "ex": "このレモンは酸っぱいです。"
  },
  {
    "id": "c1_315",
    "kanji": "違う",
    "kana": "ちがう",
    "fr": "être différent / faux",
    "ex": "電話番号が違います。"
  },
  {
    "id": "c1_316",
    "kanji": "細い",
    "kana": "ほそい",
    "fr": "fin / mince",
    "ex": "彼女は足が細いです。"
  },
  {
    "id": "c1_317",
    "kanji": "三つ",
    "kana": "みっつ",
    "fr": "trois (objets)",
    "ex": "みかんを三つ食べました。"
  },
  {
    "id": "c1_318",
    "kanji": "八日",
    "kana": "ようか",
    "fr": "huit jours / le 8 du mois",
    "ex": "八日にテストがあります。"
  },
  {
    "id": "c1_319",
    "kanji": "高校生",
    "kana": "こうこうせい",
    "fr": "lycéen",
    "ex": "妹は高校生です。"
  },
  {
    "id": "c1_320",
    "kanji": "上手",
    "kana": "じょうず",
    "fr": "doué / habile",
    "ex": "彼は歌が上手です。"
  },
  {
    "id": "c1_321",
    "kanji": "強い",
    "kana": "つよい",
    "fr": "fort",
    "ex": "今日は風が強いです。"
  },
  {
    "id": "c1_322",
    "kanji": "七",
    "kana": "なな",
    "fr": "sept",
    "ex": "七時に起きます。"
  },
  {
    "id": "c1_323",
    "kanji": "二十日",
    "kana": "はつか",
    "fr": "vingt jours / le 20",
    "ex": "二十日に旅行へ行きます。"
  },
  {
    "id": "c1_324",
    "kanji": "左",
    "kana": "ひだり",
    "fr": "gauche",
    "ex": "左に曲がってください。"
  },
  {
    "id": "c1_325",
    "kanji": "二日",
    "kana": "ふつか",
    "fr": "deux jours / le 2 du mois",
    "ex": "二日間、雨が降りました。"
  },
  {
    "id": "c1_326",
    "kanji": "四つ",
    "kana": "よっつ",
    "fr": "quatre (objets)",
    "ex": "椅子が四つあります。"
  },
  {
    "id": "c1_327",
    "kanji": "暖かい",
    "kana": "あたたかい",
    "fr": "chaud (climat)",
    "ex": "今日は暖かいです。"
  },
  {
    "id": "c1_328",
    "kanji": "有る",
    "kana": "ある",
    "fr": "exister / avoir",
    "ex": "机の上に本が有ります。"
  },
  {
    "id": "c1_329",
    "kanji": "良い",
    "kana": "いい",
    "fr": "bon / bien",
    "ex": "今日は良い天気です。"
  },
  {
    "id": "c1_330",
    "kanji": "五つ",
    "kana": "いつつ",
    "fr": "cinq (objets)",
    "ex": "かばんが五つあります。"
  },
  {
    "id": "c1_331",
    "kanji": "妹",
    "kana": "いもうと",
    "fr": "sœur cadette",
    "ex": "妹は中学生です。"
  },
  {
    "id": "c1_332",
    "kanji": "上",
    "kana": "うえ",
    "fr": "au-dessus / en haut",
    "ex": "机の上にパソコンがあります。"
  },
  {
    "id": "c1_333",
    "kanji": "動く",
    "kana": "うごく",
    "fr": "se déplacer / bouger",
    "ex": "この時計は動きません。"
  },
  {
    "id": "c1_334",
    "kanji": "駅",
    "kana": "えき",
    "fr": "gare",
    "ex": "駅まで歩きます。"
  },
  {
    "id": "c1_335",
    "kanji": "おいしい",
    "kana": "おいしい",
    "fr": "délicieux",
    "ex": "このラーメンはおいしいです。"
  },
  {
    "id": "c1_336",
    "kanji": "大きい",
    "kana": "おおきい",
    "fr": "grand",
    "ex": "大きい犬がいます。"
  },
  {
    "id": "c1_337",
    "kanji": "弟",
    "kana": "おとうと",
    "fr": "jeune frère",
    "ex": "弟はゲームが好きです。"
  },
  {
    "id": "c1_338",
    "kanji": "男",
    "kana": "おとこ",
    "fr": "homme",
    "ex": "あそこに男の人がいます。"
  },
  {
    "id": "c1_339",
    "kanji": "大人",
    "kana": "おとな",
    "fr": "adulte",
    "ex": "彼はもう大人です。"
  },
  {
    "id": "c1_340",
    "kanji": "お願い",
    "kana": "おねがい",
    "fr": "s'il te plaît / demande",
    "ex": "これをお願いします。"
  },
  {
    "id": "c1_341",
    "kanji": "女",
    "kana": "おんな",
    "fr": "femme",
    "ex": "女の人が話しています。"
  },
  {
    "id": "c1_342",
    "kanji": "金",
    "kana": "かね",
    "fr": "argent (monnaie)",
    "ex": "お金がありません。"
  },
  {
    "id": "c1_343",
    "kanji": "彼",
    "kana": "かれ",
    "fr": "il / petit ami",
    "ex": "彼は学生です。"
  },
  {
    "id": "c1_344",
    "kanji": "昨日",
    "kana": "きのう",
    "fr": "hier",
    "ex": "昨日は休みでした。"
  },
  {
    "id": "c1_345",
    "kanji": "奇麗",
    "kana": "きれい",
    "fr": "beau / propre",
    "ex": "部屋を奇麗にします。"
  },
  {
    "id": "c1_346",
    "kanji": "口",
    "kana": "くち",
    "fr": "bouche",
    "ex": "口を開けてください。"
  },
  {
    "id": "c1_347",
    "kanji": "五",
    "kana": "ご",
    "fr": "cinq",
    "ex": "五人で遊びます。"
  },
  {
    "id": "c1_348",
    "kanji": "九日",
    "kana": "ここのか",
    "fr": "neuf jours / le 9 du mois",
    "ex": "九日に出発します。"
  },
  {
    "id": "c1_349",
    "kanji": "九つ",
    "kana": "ここのつ",
    "fr": "neuf (objets)",
    "ex": "りんごが九つあります。"
  },
  {
    "id": "c1_350",
    "kanji": "答える",
    "kana": "こたえる",
    "fr": "répondre",
    "ex": "質問に答えてください。"
  },
  {
    "id": "c1_351",
    "kanji": "先",
    "kana": "さき",
    "fr": "devant / avant (bout)",
    "ex": "お先に失礼します。"
  },
  {
    "id": "c1_352",
    "kanji": "寒い",
    "kana": "さむい",
    "fr": "froid",
    "ex": "冬は寒いです。"
  },
  {
    "id": "c1_353",
    "kanji": "四",
    "kana": "し",
    "fr": "quatre",
    "ex": "四月に日本へ行きます。"
  },
  {
    "id": "c1_354",
    "kanji": "下",
    "kana": "した",
    "fr": "sous / en bas",
    "ex": "机の下に猫がいます。"
  },
  {
    "id": "c1_355",
    "kanji": "大丈夫",
    "kana": "だいじょうぶ",
    "fr": "ça va / pas de problème",
    "ex": "大丈夫ですか。"
  },
  {
    "id": "c1_356",
    "kanji": "出す",
    "kana": "だす",
    "fr": "sortir qqch / soumettre",
    "ex": "宿題を出してください。"
  },
  {
    "id": "c1_357",
    "kanji": "小さい",
    "kana": "ちいさい",
    "fr": "petit",
    "ex": "小さい車を買いました。"
  },
  {
    "id": "c1_358",
    "kanji": "父",
    "kana": "ちち",
    "fr": "père",
    "ex": "父は医者です。"
  },
  {
    "id": "c1_359",
    "kanji": "一日",
    "kana": "ついたち",
    "fr": "le 1er du mois",
    "ex": "一日に帰ります。"
  },
  {
    "id": "c1_360",
    "kanji": "月",
    "kana": "つき",
    "fr": "mois / lune",
    "ex": "月が綺麗です。"
  },
  {
    "id": "c1_361",
    "kanji": "妻",
    "kana": "つま",
    "fr": "épouse",
    "ex": "妻は料理が上手です。"
  },
  {
    "id": "c1_362",
    "kanji": "冷たい",
    "kana": "つめたい",
    "fr": "froid (au toucher)",
    "ex": "冷たい水を飲みます。"
  },
  {
    "id": "c1_363",
    "kanji": "手",
    "kana": "て",
    "fr": "main",
    "ex": "手を洗います。"
  },
  {
    "id": "c1_364",
    "kanji": "十日",
    "kana": "とおか",
    "fr": "dix jours / le 10 du mois",
    "ex": "十日に会いましょう。"
  },
  {
    "id": "c1_365",
    "kanji": "時々",
    "kana": "ときどき",
    "fr": "parfois",
    "ex": "時々、映画を見ます。"
  },
  {
    "id": "c1_366",
    "kanji": "夏",
    "kana": "なつ",
    "fr": "été",
    "ex": "夏は海に行きます。"
  },
  {
    "id": "c1_367",
    "kanji": "七つ",
    "kana": "ななつ",
    "fr": "sept (objets)",
    "ex": "みかんを七つ食べました。"
  },
  {
    "id": "c1_368",
    "kanji": "何",
    "kana": "なに",
    "fr": "quoi",
    "ex": "これは何ですか。"
  },
  {
    "id": "c1_369",
    "kanji": "七日",
    "kana": "なのか",
    "fr": "sept jours / le 7 du mois",
    "ex": "七日にテストがあります。"
  },
  {
    "id": "c1_370",
    "kanji": "母",
    "kana": "はは",
    "fr": "mère",
    "ex": "母は五十歳です。"
  },
  {
    "id": "c1_371",
    "kanji": "人",
    "kana": "ひと",
    "fr": "personnes",
    "ex": "あの人は誰ですか。"
  },
  {
    "id": "c1_372",
    "kanji": "一人",
    "kana": "ひとり",
    "fr": "une personne / seul",
    "ex": "一人で旅行します。"
  },
  {
    "id": "c1_373",
    "kanji": "百",
    "kana": "ひゃく",
    "fr": "cent",
    "ex": "これは百円です。"
  },
  {
    "id": "c1_374",
    "kanji": "方",
    "kana": "ほう",
    "fr": "direction / façon",
    "ex": "こっちの方が好きです。"
  },
  {
    "id": "c1_375",
    "kanji": "他",
    "kana": "ほか",
    "fr": "autres",
    "ex": "他の本を見せてください。"
  },
  {
    "id": "c1_376",
    "kanji": "僕",
    "kana": "ぼく",
    "fr": "je (utilisé par les hommes)",
    "ex": "僕は学生です。"
  },
  {
    "id": "c1_377",
    "kanji": "欲しい",
    "kana": "ほしい",
    "fr": "vouloir (un objet)",
    "ex": "新しい靴が欲しいです。"
  },
  {
    "id": "c1_378",
    "kanji": "万",
    "kana": "まん",
    "fr": "dix mille",
    "ex": "一万円持っています。"
  },
  {
    "id": "c1_379",
    "kanji": "見える",
    "kana": "みえる",
    "fr": "apparaître / être visible",
    "ex": "ここから山が見えます。"
  },
  {
    "id": "c1_380",
    "kanji": "店",
    "kana": "みせ",
    "fr": "boutique",
    "ex": "あの店は安いです。"
  },
  {
    "id": "c1_381",
    "kanji": "道",
    "kana": "みち",
    "fr": "route / chemin",
    "ex": "この道をまっすぐ行きます。"
  },
  {
    "id": "c1_382",
    "kanji": "目",
    "kana": "め",
    "fr": "œil",
    "ex": "目が痛いです。"
  },
  {
    "id": "c1_383",
    "kanji": "八つ",
    "kana": "やっつ",
    "fr": "huit (objets)",
    "ex": "みかんを八つ買いました。"
  },
  {
    "id": "c1_384",
    "kanji": "止める",
    "kana": "やめる",
    "fr": "arrêter / cesser",
    "ex": "明日から禁煙をやめます。"
  },
  {
    "id": "c1_385",
    "kanji": "四日",
    "kana": "よっか",
    "fr": "quatre jours / le 4 du mois",
    "ex": "四日に帰ります。"
  },
  {
    "id": "c1_386",
    "kanji": "夜",
    "kana": "よる",
    "fr": "nuit",
    "ex": "夜は早く寝ます。"
  },
  {
    "id": "c1_387",
    "kanji": "四",
    "kana": "よん",
    "fr": "quatre",
    "ex": "四時に会議があります。"
  },
  {
    "id": "c1_388",
    "kanji": "来年",
    "kana": "らいねん",
    "fr": "l'année prochaine",
    "ex": "来年、日本へ留学します。"
  },
  {
    "id": "c1_389",
    "kanji": "六",
    "kana": "ろく",
    "fr": "six",
    "ex": "六時半に起きます。"
  },
  {
    "id": "c1_390",
    "kanji": "悪い",
    "kana": "わるい",
    "fr": "mauvais",
    "ex": "今日は気分が悪いです。"
  },
  {
    "id": "c1_391",
    "kanji": "お手洗い",
    "kana": "おてあらい",
    "fr": "toilettes",
    "ex": "お手洗いはどこですか。"
  },
  {
    "id": "c1_392",
    "kanji": "ご主人",
    "kana": "ごしゅじん",
    "fr": "mari (poli)",
    "ex": "ご主人はお元気ですか。"
  },
  {
    "id": "c1_393",
    "kanji": "本当に",
    "kana": "ほんとうに",
    "fr": "vraiment",
    "ex": "本当に美味しいですね。"
  },
  {
    "id": "c1_394",
    "kanji": "自分",
    "kana": "じぶん",
    "fr": "moi-même",
    "ex": "自分で料理を作ります。"
  },
  {
    "id": "c1_395",
    "kanji": "なる",
    "kana": "なる",
    "fr": "devenir",
    "ex": "先生になります。"
  },
  {
    "id": "c1_396",
    "kanji": "ため",
    "kana": "ため",
    "fr": "à cause de / pour",
    "ex": "家族のために働きます。"
  },
  {
    "id": "c1_397",
    "kanji": "円",
    "kana": "えん",
    "fr": "cercle / yen",
    "ex": "円を書きます。"
  },
  {
    "id": "c1_398",
    "kanji": "場合",
    "kana": "ばあい",
    "fr": "cas / situation",
    "ex": "雨の場合、中止です。"
  },
  {
    "id": "c1_399",
    "kanji": "休む",
    "kana": "やすむ",
    "fr": "se reposer / être absent",
    "ex": "今日は会社を休みます。"
  },
  {
    "id": "c1_400",
    "kanji": "見つかる",
    "kana": "みつかる",
    "fr": "être trouvé",
    "ex": "鍵が見つかりました。"
  },
  {
    "id": "c1_401",
    "kanji": "問題",
    "kana": "もんだい",
    "fr": "problème",
    "ex": "この問題は難しいです。"
  },
  {
    "id": "c1_402",
    "kanji": "開発",
    "kana": "かいはつ",
    "fr": "développement",
    "ex": "新しいシステムを開発します。"
  },
  {
    "id": "c1_403",
    "kanji": "事件",
    "kana": "じけん",
    "fr": "incident / affaire",
    "ex": "大きな事件が起きました。"
  },
  {
    "id": "c1_404",
    "kanji": "必要",
    "kana": "ひつよう",
    "fr": "besoin / nécessaire",
    "ex": "準備が必要です。"
  },
  {
    "id": "c1_405",
    "kanji": "企業",
    "kana": "きぎょう",
    "fr": "entreprise",
    "ex": "大きな企業で働きます。"
  },
  {
    "id": "c1_406",
    "kanji": "行う",
    "kana": "おこなう",
    "fr": "conduire / exécuter",
    "ex": "会議を行います。"
  },
  {
    "id": "c1_407",
    "kanji": "現在",
    "kana": "げんざい",
    "fr": "actuellement",
    "ex": "現在、東京に住んでいます。"
  },
  {
    "id": "c1_408",
    "kanji": "利用",
    "kana": "りよう",
    "fr": "utiliser",
    "ex": "電車を利用します。"
  },
  {
    "id": "c1_409",
    "kanji": "首相",
    "kana": "しゅしょう",
    "fr": "premier ministre",
    "ex": "首相が演説します。"
  },
  {
    "id": "c1_410",
    "kanji": "持つ",
    "kana": "もつ",
    "fr": "avoir / porter",
    "ex": "傘を持っていますか。"
  },
  {
    "id": "c1_411",
    "kanji": "政府",
    "kana": "せいふ",
    "fr": "gouvernement",
    "ex": "政府の政策。"
  },
  {
    "id": "c1_412",
    "kanji": "発表",
    "kana": "はっぴょう",
    "fr": "annonce",
    "ex": "結果を発表します。"
  },
  {
    "id": "c1_413",
    "kanji": "開く",
    "kana": "あく",
    "fr": "s'ouvrir",
    "ex": "ドアが開きました。"
  },
  {
    "id": "c1_414",
    "kanji": "受ける",
    "kana": "うける",
    "fr": "recevoir / passer (examen)",
    "ex": "試験を受けます。"
  },
  {
    "id": "c1_415",
    "kanji": "より",
    "kana": "より",
    "fr": "à partir de / que (comparatif)",
    "ex": "東京より大阪の方が近いです。"
  },
  {
    "id": "c1_416",
    "kanji": "昨年",
    "kana": "さくねん",
    "fr": "l'année dernière",
    "ex": "昨年、卒業しました。"
  },
  {
    "id": "c1_417",
    "kanji": "情報",
    "kana": "じょうほう",
    "fr": "information",
    "ex": "情報を集めます。"
  },
  {
    "id": "c1_418",
    "kanji": "示す",
    "kana": "しめす",
    "fr": "montrer / indiquer",
    "ex": "道を指で示します。"
  },
  {
    "id": "c1_419",
    "kanji": "建設",
    "kana": "けんせつ",
    "fr": "construction",
    "ex": "新しいビルを建設中です。"
  },
  {
    "id": "c1_420",
    "kanji": "販売",
    "kana": "はんばい",
    "fr": "vente",
    "ex": "車を販売します。"
  },
  {
    "id": "c1_421",
    "kanji": "治る",
    "kana": "なおる",
    "fr": "guérir",
    "ex": "風邪が治りました。"
  },
  {
    "id": "c1_422",
    "kanji": "機能",
    "kana": "きのう",
    "fr": "fonction",
    "ex": "このカメラには新しい機能があります。"
  },
  {
    "id": "c1_423",
    "kanji": "研究",
    "kana": "けんきゅう",
    "fr": "recherche",
    "ex": "大学で日本語を研究します。"
  },
  {
    "id": "c1_424",
    "kanji": "一方",
    "kana": "いっぽう",
    "fr": "d'autre part",
    "ex": "夏は暑い。一方、冬は寒いです。"
  },
  {
    "id": "c1_425",
    "kanji": "ドル",
    "kana": "ドル",
    "fr": "dollar",
    "ex": "百ドル払います。"
  },
  {
    "id": "c1_426",
    "kanji": "システム",
    "kana": "システム",
    "fr": "système",
    "ex": "システムを修理します。"
  },
  {
    "id": "c1_427",
    "kanji": "頃",
    "kana": "ころ",
    "fr": "à l'époque / vers (moment)",
    "ex": "子供の頃の話。"
  },
  {
    "id": "c1_428",
    "kanji": "対",
    "kana": "たい",
    "fr": "contre / versus",
    "ex": "日本対ブラジル。"
  },
  {
    "id": "c1_429",
    "kanji": "方法",
    "kana": "ほうほう",
    "fr": "méthode",
    "ex": "勉強の方法を教えます。"
  },
  {
    "id": "c1_430",
    "kanji": "以上",
    "kana": "いじょう",
    "fr": "plus que / ça suffit",
    "ex": "以上です。"
  },
  {
    "id": "c1_431",
    "kanji": "最近",
    "kana": "さいきん",
    "fr": "récemment",
    "ex": "最近、忙しいです。"
  },
  {
    "id": "c1_432",
    "kanji": "今後",
    "kana": "こんご",
    "fr": "désormais / à l'avenir",
    "ex": "今後は気をつけます。"
  },
  {
    "id": "c1_433",
    "kanji": "世界",
    "kana": "せかい",
    "fr": "monde",
    "ex": "世界を旅行したいです。"
  },
  {
    "id": "c1_434",
    "kanji": "用いる",
    "kana": "もちいる",
    "fr": "utiliser",
    "ex": "道具を用います。"
  },
  {
    "id": "c1_435",
    "kanji": "語る",
    "kana": "かたる",
    "fr": "raconter / parler",
    "ex": "昔の話を語ります。"
  },
  {
    "id": "c1_436",
    "kanji": "コンピューター",
    "kana": "コンピューター",
    "fr": "ordinateur",
    "ex": "コンピューターで仕事をします。"
  },
  {
    "id": "c1_437",
    "kanji": "中心",
    "kana": "ちゅうしん",
    "fr": "centre",
    "ex": "町の中心に行きます。"
  },
  {
    "id": "c1_438",
    "kanji": "やる",
    "kana": "やる",
    "fr": "faire",
    "ex": "明日はサッカーをやります。"
  },
  {
    "id": "c1_439",
    "kanji": "意味",
    "kana": "いみ",
    "fr": "signification",
    "ex": "この言葉の意味は何ですか。"
  },
  {
    "id": "c1_440",
    "kanji": "計画",
    "kana": "けいかく",
    "fr": "plan / projet",
    "ex": "旅行の計画を立てます。"
  },
  {
    "id": "c1_441",
    "kanji": "影響",
    "kana": "えいきょう",
    "fr": "influence",
    "ex": "環境に影響します。"
  },
  {
    "id": "c1_442",
    "kanji": "増える",
    "kana": "ふえる",
    "fr": "augmenter",
    "ex": "人口が増えています。"
  },
  {
    "id": "c1_443",
    "kanji": "選ぶ",
    "kana": "えらぶ",
    "fr": "choisir",
    "ex": "好きな色を選んでください。"
  },
  {
    "id": "c1_444",
    "kanji": "経済",
    "kana": "けいざい",
    "fr": "économie",
    "ex": "経済を勉強します。"
  },
  {
    "id": "c1_445",
    "kanji": "導入",
    "kana": "どうにゅう",
    "fr": "introduction / adoption",
    "ex": "新しいシステムを導入します。"
  },
  {
    "id": "c1_446",
    "kanji": "生活",
    "kana": "せいかつ",
    "fr": "vie quotidienne",
    "ex": "日本での生活は楽しいです。"
  },
  {
    "id": "c1_447",
    "kanji": "進める",
    "kana": "すすめる",
    "fr": "avancer",
    "ex": "会議を進めます。"
  },
  {
    "id": "c1_448",
    "kanji": "関係",
    "kana": "かんけい",
    "fr": "relation",
    "ex": "二人の関係が良いです。"
  },
  {
    "id": "c1_449",
    "kanji": "続ける",
    "kana": "つづける",
    "fr": "continuer",
    "ex": "勉強を続けます。"
  },
  {
    "id": "c1_450",
    "kanji": "ロボット",
    "kana": "ロボット",
    "fr": "robot",
    "ex": "ロボットを作ります。"
  },
  {
    "id": "c1_451",
    "kanji": "ほとんど",
    "kana": "ほとんど",
    "fr": "presque tout",
    "ex": "ほとんど食べました。"
  },
  {
    "id": "c1_452",
    "kanji": "国内",
    "kana": "こくない",
    "fr": "domestique / intérieur",
    "ex": "国内旅行へ行きます。"
  },
  {
    "id": "c1_453",
    "kanji": "分野",
    "kana": "ぶんや",
    "fr": "champ / domaine",
    "ex": "専門の分野です。"
  },
  {
    "id": "c1_454",
    "kanji": "会社",
    "kana": "かいしゃ",
    "fr": "entreprise",
    "ex": "会社へ行きます。"
  },
  {
    "id": "c1_455",
    "kanji": "関",
    "kana": "かん",
    "fr": "barrière / connexion",
    "ex": "関係。"
  },
  {
    "id": "c1_456",
    "kanji": "状態",
    "kana": "じょうたい",
    "fr": "situation / état",
    "ex": "今の状態を説明します。"
  },
  {
    "id": "c1_457",
    "kanji": "大統領",
    "kana": "だいとうりょう",
    "fr": "président",
    "ex": "大統領と会います。"
  },
  {
    "id": "c1_458",
    "kanji": "対象",
    "kana": "たいしょう",
    "fr": "sujet / cible",
    "ex": "調査の対象。"
  },
  {
    "id": "c1_459",
    "kanji": "処理",
    "kana": "しょり",
    "fr": "traitement / gestion",
    "ex": "データを処理します。"
  },
  {
    "id": "c1_460",
    "kanji": "女性",
    "kana": "じょせい",
    "fr": "femme",
    "ex": "女性が立っています。"
  },
  {
    "id": "c1_461",
    "kanji": "家",
    "kana": "いえ",
    "fr": "maison",
    "ex": "家へ帰ります。"
  },
  {
    "id": "c1_462",
    "kanji": "パソコン",
    "kana": "パソコン",
    "fr": "ordinateur personnel",
    "ex": "パソコンを使います。"
  },
  {
    "id": "c1_463",
    "kanji": "解決",
    "kana": "かいけつ",
    "fr": "solution",
    "ex": "問題を解決します。"
  },
  {
    "id": "c1_464",
    "kanji": "実現",
    "kana": "じつげん",
    "fr": "réalisation",
    "ex": "夢を実現します。"
  },
  {
    "id": "c1_465",
    "kanji": "多く",
    "kana": "おおく",
    "fr": "beaucoup",
    "ex": "多くの人がいます。"
  },
  {
    "id": "c1_466",
    "kanji": "動き",
    "kana": "うごき",
    "fr": "mouvement",
    "ex": "体の動き。"
  },
  {
    "id": "c1_467",
    "kanji": "話",
    "kana": "はなし",
    "fr": "histoire / discussion",
    "ex": "面白い話を聞きました。"
  },
  {
    "id": "c1_468",
    "kanji": "価格",
    "kana": "かかく",
    "fr": "prix",
    "ex": "価格が高いです。"
  },
  {
    "id": "c1_469",
    "kanji": "上がる",
    "kana": "あがる",
    "fr": "monter",
    "ex": "値段が上がります。"
  },
  {
    "id": "c1_470",
    "kanji": "もう",
    "kana": "もう",
    "fr": "déjà",
    "ex": "もう十一時です。"
  },
  {
    "id": "c1_471",
    "kanji": "集める",
    "kana": "あつめる",
    "fr": "collecter",
    "ex": "切手を集めます。"
  },
  {
    "id": "c1_472",
    "kanji": "声",
    "kana": "こえ",
    "fr": "voix",
    "ex": "声が小さいです。"
  },
  {
    "id": "c1_473",
    "kanji": "初めて",
    "kana": "はじめて",
    "fr": "pour la première fois",
    "ex": "日本へ初めて来ました。"
  },
  {
    "id": "c1_474",
    "kanji": "明らか",
    "kana": "あきらか",
    "fr": "clair / évident",
    "ex": "それは明らかです。"
  },
  {
    "id": "c1_475",
    "kanji": "一部",
    "kana": "いちぶ",
    "fr": "une partie",
    "ex": "一部の人だけ。"
  },
  {
    "id": "c1_476",
    "kanji": "調査",
    "kana": "ちょうさ",
    "fr": "enquête",
    "ex": "調査を始めます。"
  },
  {
    "id": "c1_477",
    "kanji": "党",
    "kana": "とう",
    "fr": "parti politique",
    "ex": "新しい党を作ります。"
  },
  {
    "id": "c1_478",
    "kanji": "変わる",
    "kana": "かわる",
    "fr": "changer",
    "ex": "季節が変わります。"
  },
  {
    "id": "c1_479",
    "kanji": "社長",
    "kana": "しゃちょう",
    "fr": "PDG / président",
    "ex": "社長と話します。"
  },
  {
    "id": "c1_480",
    "kanji": "全国",
    "kana": "ぜんこく",
    "fr": "dans tout le pays",
    "ex": "全国を旅行します。"
  },
  {
    "id": "c1_481",
    "kanji": "地域",
    "kana": "ちいき",
    "fr": "région",
    "ex": "この地域は寒いです。"
  },
  {
    "id": "c1_482",
    "kanji": "重要",
    "kana": "じゅうよう",
    "fr": "important",
    "ex": "これは重要な話です。"
  },
  {
    "id": "c1_483",
    "kanji": "姿",
    "kana": "すがた",
    "fr": "apparence / silhouette",
    "ex": "彼女の姿。"
  },
  {
    "id": "c1_484",
    "kanji": "先ず",
    "kana": "まず",
    "fr": "tout d'abord",
    "ex": "まず、名前を書いてください。"
  },
  {
    "id": "c1_485",
    "kanji": "昭和",
    "kana": "しょうわ",
    "fr": "ère Showa",
    "ex": "昭和の時代。"
  },
  {
    "id": "c1_486",
    "kanji": "社会",
    "kana": "しゃかい",
    "fr": "société",
    "ex": "社会を勉強します。"
  },
  {
    "id": "c1_487",
    "kanji": "プログラム",
    "kana": "プログラム",
    "fr": "programme",
    "ex": "プログラムを書きます。"
  },
  {
    "id": "c1_488",
    "kanji": "期待",
    "kana": "きたい",
    "fr": "attente / espoir",
    "ex": "彼を期待しています。"
  },
  {
    "id": "c1_489",
    "kanji": "ちから",
    "kana": "ちから",
    "fr": "pouvoir / force",
    "ex": "ちからを出します。"
  },
  {
    "id": "c1_490",
    "kanji": "除く",
    "kana": "のぞく",
    "fr": "sauf / exclure",
    "ex": "彼を除いてみんな行きました。"
  },
  {
    "id": "c1_491",
    "kanji": "一般",
    "kana": "いっぱん",
    "fr": "général",
    "ex": "一般の人。"
  },
  {
    "id": "c1_492",
    "kanji": "今回",
    "kana": "こんかい",
    "fr": "cette fois",
    "ex": "今回は勝ちました。"
  },
  {
    "id": "c1_493",
    "kanji": "普及",
    "kana": "ふきゅう",
    "fr": "diffusion / popularisation",
    "ex": "スマホが普及しています。"
  },
  {
    "id": "c1_494",
    "kanji": "表現",
    "kana": "ひょうげん",
    "fr": "expression",
    "ex": "新しい表現を覚えます。"
  },
  {
    "id": "c1_495",
    "kanji": "作業",
    "kana": "さぎょう",
    "fr": "travail / opération",
    "ex": "作業を始めます。"
  },
  {
    "id": "c1_496",
    "kanji": "予定",
    "kana": "よてい",
    "fr": "programme / prévu",
    "ex": "明日の予定は何ですか。"
  },
  {
    "id": "c1_497",
    "kanji": "工場",
    "kana": "こうじょう",
    "fr": "usine",
    "ex": "工場で働きます。"
  },
  {
    "id": "c1_498",
    "kanji": "よく",
    "kana": "よく",
    "fr": "souvent",
    "ex": "よく会いますね。"
  },
  {
    "id": "c1_499",
    "kanji": "生産",
    "kana": "せいさん",
    "fr": "production",
    "ex": "車を生産します。"
  },
  {
    "id": "c1_500",
    "kanji": "政権",
    "kana": "せいけん",
    "fr": "administration / pouvoir",
    "ex": "新しい政権。"
  }
]
